manicode/__init__.py
manicode-0.1.0.dist-info/LICENSE
manicode-0.1.0.dist-info/METADATA
manicode-0.1.0.dist-info/WHEEL
manicode-0.1.0.dist-info/entry_points.txt
manicode-0.1.0.dist-info/top_level.txt
manicode-0.1.0.dist-info/RECORD
