Metadata-Version: 2.1
Name: manicode
Version: 0.1.0
Summary: An AI-powered coding assistant (coming soon)
Author-email: Manicode Team <james@manifold.markets>
License: MIT License
Project-URL: Homepage, https://github.com/manifoldmarkets/manicode
Project-URL: Bug Tracker, https://github.com/manifoldmarkets/manicode/issues
Classifier: Development Status :: 2 - Pre-Alpha
Classifier: Intended Audience :: Developers
Classifier: License :: OSI Approved :: MIT License
Classifier: Programming Language :: Python :: 3
Classifier: Programming Language :: Python :: 3.6
Classifier: Programming Language :: Python :: 3.7
Classifier: Programming Language :: Python :: 3.8
Classifier: Programming Language :: Python :: 3.9
Requires-Python: >=3.6
License-File: LICENSE
